blocksets/__init__.py
blocksets/example_use.py
blocksets/classes/__init__.py
blocksets/classes/block.py
blocksets/classes/blockset.py
blocksets/classes/exceptions.py
blocksets-0.3.1.dist-info/LICENSE
blocksets-0.3.1.dist-info/METADATA
blocksets-0.3.1.dist-info/WHEEL
blocksets-0.3.1.dist-info/top_level.txt
blocksets-0.3.1.dist-info/RECORD
