Metadata-Version: 2.1
Name: blocksets
Version: 0.3.1
Summary: Python package for performing set type operations on any layout of discrete space in any dimension.
Author-email: Dave Budd <maildavebudd@gmail.com>
Project-URL: Homepage, https://github.com/daveisagit/blocksets
Project-URL: Documentation, https://blocksets.readthedocs.io/
Project-URL: Issues, https://github.com/daveisagit/blocksets/issues
Keywords: blocks,compare,cubes,cubiods,dimension,grid,integer,intersect,intervals,lattice,orthogonal,overlap,normalise,pixels,points,ranges,rectangles,sets,space,squares,union,units
Classifier: Programming Language :: Python :: 3
Classifier: Operating System :: OS Independent
Requires-Python: >=3.11
License-File: LICENSE
